exploit.py
testt_test-99.0.1.dist-info/METADATA
testt_test-99.0.1.dist-info/WHEEL
testt_test-99.0.1.dist-info/top_level.txt
testt_test-99.0.1.dist-info/RECORD
